{
	"movies": [
  	{
    	"Title": "Avatar",
    	"Year": "2009",
    	"Genre": ["Action", "Adventure", "Fantasy"],
    	"Poster": "http://ia.media-imdb.com/images/M/MV5BMTYwOTEwNjAzMl5BMl5BanBnXkFtZTcwODc5MTUwMw@@._V1_SX300.jpg",
  	},
  	{
    	"Title": "I Am Legend",
    	"Year": "2007",
    	"Genre": ["Drama", "Horror", "Sci-Fi"],
    	"Poster": "http://ia.media-imdb.com/images/M/MV5BMTU4NzMyNDk1OV5BMl5BanBnXkFtZTcwOTEwMzU1MQ@@._V1_SX300.jpg",
  	},
  	{
    	"Title": "300",
    	"Year": "2006",
    	"Genre": ["Action", "Drama", "Fantasy"],
    	"Poster": "http://ia.media-imdb.com/images/M/MV5BMjAzNTkzNjcxNl5BMl5BanBnXkFtZTYwNDA4NjE3._V1_SX300.jpg",
  	},
  	{
    	"Title": "The Avengers",
    	"Year": "2012",
    	"Genre": ["Action", "Sci-Fi", "Thriller"],
    	"Poster": "http://ia.media-imdb.com/images/M/MV5BMTk2NTI1MTU4N15BMl5BanBnXkFtZTcwODg0OTY0Nw@@._V1_SX300.jpg",
  	},
  	{
    	"Title": "The Wolf of Wall Street",
    	"Year": "2013",
    	"Genre": ["Biography", "Comedy", "Crime"],
    	"Poster": "http://ia.media-imdb.com/images/M/MV5BMjIxMjgxNTk0MF5BMl5BanBnXkFtZTgwNjIyOTg2MDE@._V1_SX300.jpg",
  	},
  	{
    	"Title": "Interstellar",
    	"Year": "2014",
    	"Genre": ["Adventure", "Drama", "Sci-Fi"],
    	"Poster": "http://ia.media-imdb.com/images/M/MV5BMjIxNTU4MzY4MF5BMl5BanBnXkFtZTgwMzM4ODI3MjE@._V1_SX300.jpg",
  	},
  	{
    	"Title": "Game of Thrones",
    	"Year": "2011",
    	"Genre": ["Adventure", "Drama", "Fantasy"],
    	"Poster": "http://ia.media-imdb.com/images/M/MV5BMjM5OTQ1MTY5Nl5BMl5BanBnXkFtZTgwMjM3NzMxODE@._V1_SX300.jpg",
  	},
  	{
    	"Title": "Vikings",
    	"Year": "2013",
    	"Genre": ["Action", "Drama", "History"],
    	"Poster": "http://ia.media-imdb.com/images/M/MV5BOTEzNzI3MDc0N15BMl5BanBnXkFtZTgwMzk1MzA5NzE@._V1_SX300.jpg",
  	},
  	{
    	"Title": "Gotham",
    	"Year": "2014",
    	"Genre": ["Action", "Crime", "Drama"],
    	"Poster": "http://ia.media-imdb.com/images/M/MV5BMTY2MjMwNDE4OV5BMl5BanBnXkFtZTgwNjI1NjU0OTE@._V1_SX300.jpg",
  	},
  	{
    	"Title": "Power",
    	"Year": "2014",
    	"Genre": ["Crime", "Drama"],
    	"Poster": "http://ia.media-imdb.com/images/M/MV5BOTA4NTkzMjUzOF5BMl5BanBnXkFtZTgwNzg5ODkxOTE@._V1_SX300.jpg",
  	},
  	{
    	"Title": "Narcos",
    	"Year": "2015",
    	"Genre": ["Biography", "Crime", "Drama"],
    	"Poster": "http://ia.media-imdb.com/images/M/MV5BMTU0ODQ4NDg2OF5BMl5BanBnXkFtZTgwNzczNTE4OTE@._V1_SX300.jpg",
  	},
  	{
    	"Title": "Doctor Strange",
    	"Year": "2016",
    	"Genre": ["Action", "Adventure", "Fantasy"],
    	"Poster": "http://ia.media-imdb.com/images/M/MV5BNjgwNzAzNjk1Nl5BMl5BanBnXkFtZTgwMzQ2NjI1OTE@._V1_SX300.jpg",
  	},
  	{
    	"Title": "Rogue One: A Star Wars Story",
    	"Year": "2016",
    	"Genre": ["Action", "Adventure", "Sci-Fi"],
    	"Poster": "https://images-na.ssl-images-amazon.com/images/M/MV5BMjQyMzI2OTA3OF5BMl5BanBnXkFtZTgwNDg5NjQ0OTE@._V1_SY1000_CR0,0,674,1000_AL_.jpg",
  	},
  	{
    	"Title": "Assassin's Creed",
    	"Year": "2016",
    	"Genre": ["Action", "Adventure", "Fantasy"],
    	"Poster": "http://ia.media-imdb.com/images/M/MV5BMTU2MTQwMjU1OF5BMl5BanBnXkFtZTgwMDA5NjU5ODE@._V1_SX300.jpg",
  	},
  	{
    	"Title": "Luke Cage",
    	"Year": "2016",
    	"Genre": ["Action", "Crime", "Drama"],
    	"Poster": "http://ia.media-imdb.com/images/M/MV5BMTcyMzc1MjI5MF5BMl5BanBnXkFtZTgwMzE4ODY2OTE@._V1_SX300.jpg",
  	}
 	]
}

